translatorAR/__init__.py
translatorAR/translatorAR.py
translatorAR-0.2.3.dist-info/LICENSE.md
translatorAR-0.2.3.dist-info/METADATA
translatorAR-0.2.3.dist-info/WHEEL
translatorAR-0.2.3.dist-info/top_level.txt
translatorAR-0.2.3.dist-info/RECORD
