Metadata-Version: 2.1
Name: translatorAR
Version: 0.2.3
Summary: A translation tool for multiple languages.
Home-page: https://pypi.org/project/translatorAR/0.1.0/
Author: Amin Boulouma
Author-email: amin@boulouma.com
License: CC BY-NC 4.0
License-File: LICENSE.md
Requires-Dist: transformers
Requires-Dist: pymupdf
Requires-Dist: tqdm
Requires-Dist: pdf2image
Requires-Dist: pytesseract
Requires-Dist: pillow
